html_cleaver/__init__.py
html_cleaver/cleaver.py
html_cleaver/handle.py
html_cleaver/util/__init__.py
html_cleaver/util/parse_html.py
html_cleaver/util/render_selenium.py
html_cleaver-0.3.0.dist-info/LICENSE.txt
html_cleaver-0.3.0.dist-info/METADATA
html_cleaver-0.3.0.dist-info/WHEEL
html_cleaver-0.3.0.dist-info/RECORD
