Metadata-Version: 2.1
Name: html-cleaver
Version: 0.3.0
Summary: cleave html headers and text
Home-page: https://github.com/PresidioVantage/html-cleaver
License: MIT
Keywords: xml,html
Author: Presidio Vantage
Author-email: presidiovantage@github.com
Requires-Python: >=3.8,<4.0
Classifier: License :: OSI Approved :: MIT License
Classifier: Programming Language :: Python :: 3
Classifier: Programming Language :: Python :: 3.8
Classifier: Programming Language :: Python :: 3.9
Classifier: Programming Language :: Python :: 3.10
Classifier: Programming Language :: Python :: 3.11
Classifier: Programming Language :: Python :: 3.12
Requires-Dist: lxml (>=4.9.3,<5.0.0)
Requires-Dist: selenium (>=4.15.2,<5.0.0)
Project-URL: Repository, https://github.com/PresidioVantage/html-cleaver
